{
  "repo": "mqengine",
  "scope": "full",
  "source_path": "C:\\MAMAKQUANT\\mqengine_lib_full",
  "remote": "github.com/CGRoths/mqengine",
  "layer": "MQENGINE",
  "package_name": "mqengine",
  "version": "0.3.0",
  "languages": ["Python", "HTML", "TOML", "Markdown"],
  "package_modules": [
    "mqengine/__init__.py",
    "mqengine/alignment.py",
    "mqengine/conditions.py",
    "mqengine/dashboard.py",
    "mqengine/engine.py",
    "mqengine/facade.py",
    "mqengine/io_sql.py",
    "mqengine/metrics.py",
    "mqengine/montecarlo.py",
    "mqengine/oms_analytics.py",
    "mqengine/portfolio.py",
    "mqengine/research.py",
    "mqengine/result.py",
    "mqengine/risk.py",
    "mqengine/schemas.py",
    "mqengine/stability.py",
    "mqengine/sweep.py",
    "mqengine/transforms.py",
    "mqengine/types.py",
    "mqengine/validation.py",
    "mqengine/vectorized.py"
  ],
  "entry_points": ["mqengine/__init__.py", "mqengine/facade.py", "mqengine/dashboard.py"],
  "high_risk_modules": ["mqengine/metrics.py", "mqengine/risk.py"],
  "lookahead_relevant_tests": [
    "tests/test_walkforward.py",
    "tests/test_research_split.py",
    "tests/test_research_protocol_splits.py",
    "tests/test_validation_signal.py",
    "tests/test_vectorized_signal_backtest.py",
    "tests/test_alignment.py"
  ],
  "tests": [
    "tests/test_adrs_compat_metrics.py",
    "tests/test_alignment.py",
    "tests/test_engine_backward_compat.py",
    "tests/test_metric_keys.py",
    "tests/test_metrics.py",
    "tests/test_portfolio.py",
    "tests/test_research_protocol_splits.py",
    "tests/test_research_split.py",
    "tests/test_validation_signal.py",
    "tests/test_vectorized_signal_backtest.py",
    "tests/test_walkforward.py"
  ],
  "examples": ["examples/nvt_sql_pattern_example.py", "examples/nvt_sweep_dashboard_example.py"],
  "templates": ["mqengine/templates/basic.html"],
  "deps": ["flask>=3.0.0", "numpy>=1.24.0", "pandas>=2.0.0"],
  "config_files": ["pyproject.toml", "mqengine.egg-info/PKG-INFO"],
  "secret_risk_files": ["PyPI-Recovery-Codes-<redacted>.txt"],
  "unmapped": [
    "public exports from __init__.py / facade.py",
    "metric/formula definitions in metrics.py (HIGH-risk; not deep-read)",
    "point-in-time correctness of splits/walk-forward (not traced)",
    "io_sql.py data source contract",
    ".agents/ .codex/ .qodo/ tooling (not product)"
  ]
}
